iproxpy/__init__.py
iproxpy-1.0.9.dist-info/LICENSE
iproxpy-1.0.9.dist-info/METADATA
iproxpy-1.0.9.dist-info/WHEEL
iproxpy-1.0.9.dist-info/top_level.txt
iproxpy-1.0.9.dist-info/RECORD
