Metadata-Version: 2.1
Name: iproxpy
Version: 1.0.9
Summary: A python package for iprox
Author-email: phage-GP <mirscope@outlook.com>
Project-URL: Homepage, https://github.com/phage-GP/iproxpy/
Project-URL: Issues, https://github.com/phage-GP/iproxpy/issues
Classifier: Programming Language :: Python :: 3
Classifier: License :: OSI Approved :: MIT License
Classifier: Operating System :: OS Independent
Requires-Python: >=3.8
License-File: LICENSE
Requires-Dist: joblib
Requires-Dist: requests
